pytrevl/__init__.py
pytrevl/chart.py
pytrevl/chart_parent_class.py
pytrevl/component.py
pytrevl/components.py
pytrevl/cube.py
pytrevl/dashboard.py
pytrevl/filter.py
pytrevl/render.py
pytrevl/style.py
pytrevl/trevl_code_generator.py
pytrevl/api/__init__.py
pytrevl/api/api.py
pytrevl/api/cube.py
pytrevl/api/cube_api.py
pytrevl/api/cube_query.py
pytrevl/api/x_middle.py
pytrevl-0.2.1.dist-info/LICENSE
pytrevl-0.2.1.dist-info/METADATA
pytrevl-0.2.1.dist-info/WHEEL
pytrevl-0.2.1.dist-info/top_level.txt
pytrevl-0.2.1.dist-info/RECORD
