Metadata-Version: 2.1
Name: pytrevl
Version: 0.2.1
Summary: Python interface to handle and modify TREVL backed visualizations
Home-page: https://github.com/trendence/pytrevl
Author: Trendence Institut GmbH
Author-email: pytrevl@trendence.com
License: MIT License
Classifier: Development Status :: 1 - Planning
Classifier: Intended Audience :: Science/Research
Classifier: License :: OSI Approved :: BSD License
Classifier: Operating System :: POSIX :: Linux
Classifier: Programming Language :: Python :: 3.9
License-File: LICENSE
Requires-Dist: numpy (>=1.23.5pandas>=1.5)
Requires-Dist: pyyaml (>=6.0)
Requires-Dist: requests (>=2.0.0)
